README.md
setup.cfg
setup.py
test/test_actualize_api.py
test/test_actualize_settings.py
test/test_actualize_task.py
test/test_analytics_api.py
test/test_analytics_task.py
test/test_box.py
test/test_calculation_detail.py
test/test_capacity.py
test/test_capacity_factor.py
test/test_cargo.py
test/test_check_result.py
test/test_compatibility_penalty.py
test/test_convert_api.py
test/test_convert_settings.py
test/test_convert_task.py
test/test_cost_penalty.py
test/test_customer.py
test/test_delivery_settings.py
test/test_facts.py
test/test_inline_response400.py
test/test_inline_response401.py
test/test_inline_response404.py
test/test_inline_response406.py
test/test_inline_response415.py
test/test_inline_response429.py
test/test_inline_response500.py
test/test_inline_response501.py
test/test_inline_response502.py
test/test_inline_response503.py
test/test_inline_response504.py
test/test_inline_response_default.py
test/test_job_fact.py
test/test_job_type.py
test/test_location.py
test/test_measurements.py
test/test_objects_metrics.py
test/test_order.py
test/test_order_cost.py
test/test_order_fact.py
test/test_order_type.py
test/test_performer.py
test/test_performer_fact.py
test/test_plan_api.py
test/test_plan_assumptions.py
test/test_plan_id.py
test/test_plan_info.py
test/test_plan_penalties.py
test/test_plan_result.py
test/test_plan_settings.py
test/test_plan_statistics.py
test/test_plan_status.py
test/test_plan_task.py
test/test_predict_api.py
test/test_predict_result.py
test/test_predict_result_window.py
test/test_predict_task.py
test/test_quality_statistics.py
test/test_rotation_type.py
test/test_routing.py
test/test_routing_matrix.py
test/test_shift.py
test/test_statistics.py
test/test_stop_statistics.py
test/test_system_api.py
test/test_tariff.py
test/test_tariff_primary.py
test/test_time_window.py
test/test_time_window_violation.py
test/test_trace_data.py
test/test_track_point.py
test/test_traffic_factor.py
test/test_transport_factor.py
test/test_transport_load.py
vrt_lss_delivery.egg-info/PKG-INFO
vrt_lss_delivery.egg-info/SOURCES.txt
vrt_lss_delivery.egg-info/dependency_links.txt
vrt_lss_delivery.egg-info/requires.txt
vrt_lss_delivery.egg-info/top_level.txt
