Metadata-Version: 1.0
Name: vrt-lss-delivery
Version: 3.9.172873
Summary: Veeroute.Delivery
Home-page: https://docs.veeroute.com/#/lss/delivery
Author: Veeroute Support Team
Author-email: support@veeroute.com
License: UNKNOWN
Keywords: OpenAPI,OpenAPI-Generator,Veeroute.Delivery
Platform: UNKNOWN
